AUTHORS.txt
LICENSE.txt
MANIFEST.in
README.txt
setup.py
beta/__init__.py
beta/admin.py
beta/forms.py
beta/listeners.py
beta/managers.py
beta/models.py
beta/urls.py
beta/views.py
beta/templates/beta/confirmation.html
beta/templates/beta/signup.html
beta/tests/__init__.py
beta/tests/models.py
beta/tests/runtests.py
beta/tests/tests.py
django_beta.egg-info/PKG-INFO
django_beta.egg-info/SOURCES.txt
django_beta.egg-info/dependency_links.txt
django_beta.egg-info/not-zip-safe
django_beta.egg-info/top_level.txt