Metadata-Version: 1.0
Name: django-beta
Version: 0.1.0
Summary: django-beta is a reusable Django application for handling pre-beta signups.
Home-page: http://github.com/revsys/django-beta
Author: Frank Wiles
Author-email: frank@revsys.com
License: LICENSE.txt
Download-URL: https://github.com/revsys/django-beta/tarball/master
Platform: UNKNOWN
Classifier: Development Status :: 4 - Beta
Classifier: Environment :: Web Environment
Classifier: Intended Audience :: Developers
Classifier: License :: OSI Approved :: BSD License
Classifier: Operating System :: OS Independent
Classifier: Programming Language :: Python
Classifier: Framework :: Django
